<?xml version="1.0" encoding="utf-8" standalone="yes"?>

<!-- $Id$ -->

<T3locallang>
    <meta type="array">
        <type>module</type>
        <description>General language labels for extension &quot;oop&quot;</description>
    </meta>
    <data type="array">
        <languageKey index="default" type="array">
            <label index="After">After</label>
            <label index="after">after</label>
            <label index="Author">Author</label>
            <label index="author">author</label>
            <label index="Browse">Browse</label>
            <label index="browse">browse</label>
            <label index="Cancel">Cancel</label>
            <label index="cancel">cancel</label>
            <label index="Category">Category</label>
            <label index="category">category</label>
            <label index="Change">Change</label>
            <label index="change">change</label>
            <label index="Clear">Clear</label>
            <label index="clear">clear</label>
            <label index="Clipboard">Clipboard</label>
            <label index="clipboard">clipboard</label>
            <label index="Close">Close</label>
            <label index="close">close</label>
            <label index="Content">Content</label>
            <label index="content">content</label>
            <label index="Control">Control</label>
            <label index="control">control</label>
            <label index="Copy">Copy</label>
            <label index="copy">copy</label>
            <label index="Create">Create</label>
            <label index="create">create</label>
            <label index="Cut">Cut</label>
            <label index="cut">cut</label>
            <label index="Day">Day</label>
            <label index="day">day</label>
            <label index="Days">Days</label>
            <label index="days">days</label>
            <label index="Delete">Delete</label>
            <label index="delete">delete</label>
            <label index="Deselect">Deselect</label>
            <label index="deselect">deselect</label>
            <label index="Dimensions">Dimensions</label>
            <label index="dimensions">dimensions</label>
            <label index="Directory">Directory</label>
            <label index="directory">directory</label>
            <label index="Document">Document</label>
            <label index="document">document</label>
            <label index="Edit">Edit</label>
            <label index="edit">edit</label>
            <label index="End">End</label>
            <label index="end">end</label>
            <label index="Exit">Exit</label>
            <label index="exit">exit</label>
            <label index="Expand">Expand</label>
            <label index="expand">expand</label>
            <label index="Export">Export</label>
            <label index="export">export</label>
            <label index="File">File</label>
            <label index="file">file</label>
            <label index="Folder">Folder</label>
            <label index="folder">folder</label>
            <label index="General">General</label>
            <label index="general">general</label>
            <label index="Global">Global</label>
            <label index="global">global</label>
            <label index="Go_back">Go back</label>
            <label index="go_back">go back</label>
            <label index="Hidden">Hidden</label>
            <label index="hidden">hidden</label>
            <label index="Hide">Hide</label>
            <label index="hide">hide</label>
            <label index="Hour">Hour</label>
            <label index="hour">hour</label>
            <label index="Hours">Hours</label>
            <label index="hours">hours</label>
            <label index="Important">Important</label>
            <label index="important">important</label>
            <label index="Info">Info</label>
            <label index="info">info</label>
            <label index="Insert">Insert</label>
            <label index="insert">insert</label>
            <label index="Inside">Inside</label>
            <label index="inside">inside</label>
            <label index="Logout">Logout</label>
            <label index="logout">logout</label>
            <label index="Menu">Menu</label>
            <label index="menu">menu</label>
            <label index="Minute">Minute</label>
            <label index="minute">minute</label>
            <label index="Minutes">Minutes</label>
            <label index="minutes">minutes</label>
            <label index="Miscellaneous">Miscellaneous</label>
            <label index="miscellaneous">miscellaneous</label>
            <label index="Month">Month</label>
            <label index="month">month</label>
            <label index="Monthes">Monthes</label>
            <label index="monthes">monthes</label>
            <label index="More">More</label>
            <label index="more">more</label>
            <label index="Move">Move</label>
            <label index="move">move</label>
            <label index="New">New</label>
            <label index="new">new</label>
            <label index="No">No</label>
            <label index="no">no</label>
            <label index="Note">Note</label>
            <label index="note">note</label>
            <label index="Open">Open</label>
            <label index="open">open</label>
            <label index="Open_in_a_new_window">Open in a new window</label>
            <label index="open_in_a_new_window">open in a new window</label>
            <label index="Options">Options</label>
            <label index="options">options</label>
            <label index="Original">Original</label>
            <label index="original">original</label>
            <label index="Page">Page</label>
            <label index="page">page</label>
            <label index="Paste">Paste</label>
            <label index="paste">paste</label>
            <label index="Path">Path</label>
            <label index="path">path</label>
            <label index="Reload">Reload</label>
            <label index="reload">reload</label>
            <label index="Remove">Remove</label>
            <label index="remove">remove</label>
            <label index="Rename">Rename</label>
            <label index="rename">rename</label>
            <label index="Revert">Revert</label>
            <label index="revert">revert</label>
            <label index="Save">Save</label>
            <label index="save">save</label>
            <label index="Search">Search</label>
            <label index="search">search</label>
            <label index="Second">Second</label>
            <label index="second">second</label>
            <label index="Seconds">Seconds</label>
            <label index="seconds">seconds</label>
            <label index="Select">Select</label>
            <label index="select">select</label>
            <label index="Select_all">Select all</label>
            <label index="select_all">select all</label>
            <label index="Selected">Selected</label>
            <label index="selected">selected</label>
            <label index="Selection">Selection</label>
            <label index="selection">selection</label>
            <label index="Show">Show</label>
            <label index="show">show</label>
            <label index="Size">Size</label>
            <label index="size">size</label>
            <label index="Start">Start</label>
            <label index="start">start</label>
            <label index="Stop">Stop</label>
            <label index="stop">stop</label>
            <label index="Table">Table</label>
            <label index="table">table</label>
            <label index="Thumbnail">Thumbnail</label>
            <label index="thumbnail">thumbnail</label>
            <label index="Thumbnails">Thumbnails</label>
            <label index="thumbnails">thumbnails</label>
            <label index="Title">Title</label>
            <label index="title">title</label>
            <label index="Unhide">Unhide</label>
            <label index="unhide">unhide</label>
            <label index="Upload">Upload</label>
            <label index="upload">upload</label>
            <label index="Version">Version</label>
            <label index="version">version</label>
            <label index="View">View</label>
            <label index="view">view</label>
            <label index="Year">Year</label>
            <label index="year">year</label>
            <label index="Years">Years</label>
            <label index="years">years</label>
            <label index="Yes">Yes</label>
            <label index="yes">yes</label>
        </languageKey>
        <languageKey index="fr" type="array">
            <label index="After">Après</label>
            <label index="after">après</label>
            <label index="Author">Auteur</label>
            <label index="author">auteur</label>
            <label index="Browse">Parcourir</label>
            <label index="browse">parcourir</label>
            <label index="Cancel">Annuler</label>
            <label index="cancel">annuler</label>
            <label index="Category">Catégorie</label>
            <label index="category">catégorie</label>
            <label index="Change">Changer</label>
            <label index="change">changer</label>
            <label index="Clear">Effacer</label>
            <label index="clear">effacer</label>
            <label index="Clipboard">Presse-papier</label>
            <label index="clipboard">presse-papier</label>
            <label index="Close">Fermer</label>
            <label index="close">fermer</label>
            <label index="Content">Contenu</label>
            <label index="content">contenu</label>
            <label index="Control">Contrôle</label>
            <label index="control">contrôle</label>
            <label index="Copy">Copier</label>
            <label index="copy">copier</label>
            <label index="Create">Créer</label>
            <label index="create">créer</label>
            <label index="Cut">Couper</label>
            <label index="cut">couper</label>
            <label index="Day">Jour</label>
            <label index="day">jour</label>
            <label index="Days">Jours</label>
            <label index="days">jours</label>
            <label index="Delete">Effacer</label>
            <label index="delete">effacer</label>
            <label index="Deselect">Désélectionner</label>
            <label index="deselect">désélectionner</label>
            <label index="Dimensions">Dimensions</label>
            <label index="dimensions">dimensions</label>
            <label index="Directory">Répertoire</label>
            <label index="directory">répertoire</label>
            <label index="Document">Document</label>
            <label index="document">document</label>
            <label index="Edit">Editer</label>
            <label index="edit">editer</label>
            <label index="End">Fin</label>
            <label index="end">fin</label>
            <label index="Exit">Quitter</label>
            <label index="exit">uitter</label>
            <label index="Expand">Etendre</label>
            <label index="expand">étendre</label>
            <label index="Export">Exporter</label>
            <label index="export">exporter</label>
            <label index="File">Fichier</label>
            <label index="file">fichier</label>
            <label index="Folder">Dossier</label>
            <label index="folder">dossier</label>
            <label index="General">Général</label>
            <label index="general">général</label>
            <label index="Global">Global</label>
            <label index="global">global</label>
            <label index="Go_back">Retour</label>
            <label index="go_back">retour</label>
            <label index="Hidden">Caché</label>
            <label index="hidden">caché</label>
            <label index="Hide">Cacher</label>
            <label index="hide">cacher</label>
            <label index="Hour">Heure</label>
            <label index="hour">heure</label>
            <label index="Hours">Heures</label>
            <label index="hours">heures</label>
            <label index="Important">Important</label>
            <label index="important">important</label>
            <label index="Info">Info</label>
            <label index="info">info</label>
            <label index="Insert">Insérer</label>
            <label index="insert">insérer</label>
            <label index="Inside">A l'intérieur</label>
            <label index="inside">a l'intérieur</label>
            <label index="Logout">Se déconnecter</label>
            <label index="logout">se déconnecter</label>
            <label index="Menu">Menu</label>
            <label index="menu">menu</label>
            <label index="Minute">Minute</label>
            <label index="minute">minute</label>
            <label index="Minutes">Minutes</label>
            <label index="minutes">minutes</label>
            <label index="Miscellaneous">Divers</label>
            <label index="miscellaneous">divers</label>
            <label index="Month">Mois</label>
            <label index="month">mois</label>
            <label index="Monthes">Mois</label>
            <label index="monthes">mois</label>
            <label index="More">Plus</label>
            <label index="more">plus</label>
            <label index="Move">Déplacer</label>
            <label index="move">déplacer</label>
            <label index="New">Nouveau</label>
            <label index="new">nouveau</label>
            <label index="No">Non</label>
            <label index="no">non</label>
            <label index="Note">Note</label>
            <label index="note">note</label>
            <label index="Open">Ouvrir</label>
            <label index="open">ouvrir</label>
            <label index="Open_in_a_new_window">Ouvrir dans une nouvelle fenêtre</label>
            <label index="open_in_a_new_window">ouvrir dans une nouvelle fenêtre</label>
            <label index="Options">Options</label>
            <label index="options">options</label>
            <label index="Original">Original</label>
            <label index="original">original</label>
            <label index="Page">Page</label>
            <label index="page">page</label>
            <label index="Paste">Coller</label>
            <label index="paste">coller</label>
            <label index="Path">Chemin</label>
            <label index="path">chemin</label>
            <label index="Reload">Recharger</label>
            <label index="reload">recharger</label>
            <label index="Remove">Effacer</label>
            <label index="remove">effacer</label>
            <label index="Rename">Renommer</label>
            <label index="rename">renommer</label>
            <label index="Revert">Revert</label>
            <label index="revert">revert</label>
            <label index="Save">Sauver</label>
            <label index="save">sauver</label>
            <label index="Search">Rechercher</label>
            <label index="search">rechercher</label>
            <label index="Second">Seconde</label>
            <label index="second">seconde</label>
            <label index="Seconds">Secondes</label>
            <label index="seconds">secondes</label>
            <label index="Select">Sélectionner</label>
            <label index="select">sélectionner</label>
            <label index="Select_all">Tout sélectionner</label>
            <label index="select_all">tout sélectionner</label>
            <label index="Selected">Sélectionné</label>
            <label index="selected">Sélectionné</label>
            <label index="Selection">Sélection</label>
            <label index="selection">sélection</label>
            <label index="Show">Voir</label>
            <label index="show">voir</label>
            <label index="Size">Taille</label>
            <label index="size">taille</label>
            <label index="Start">Début</label>
            <label index="start">début</label>
            <label index="Stop">Stop</label>
            <label index="stop">stop</label>
            <label index="Table">Table</label>
            <label index="table">table</label>
            <label index="Thumbnail">Vignette</label>
            <label index="thumbnail">vignette</label>
            <label index="Thumbnails">Vignettes</label>
            <label index="thumbnails">vignettes</label>
            <label index="Title">Titre</label>
            <label index="title">titre</label>
            <label index="Unhide">Rendre visible</label>
            <label index="unhide">rendre visible</label>
            <label index="Upload">Télécharger</label>
            <label index="upload">télécharger</label>
            <label index="Version">Version</label>
            <label index="version">version</label>
            <label index="View">Voir</label>
            <label index="view">voir</label>
            <label index="Year">Année</label>
            <label index="year">année</label>
            <label index="Years">Années</label>
            <label index="years">années</label>
            <label index="Yes">Oui</label>
            <label index="yes">oui</label>
        </languageKey>
    </data>
</T3locallang>
